crypo/__init__.py
crypo-0.0.3.dist-info/METADATA
crypo-0.0.3.dist-info/WHEEL
crypo-0.0.3.dist-info/top_level.txt
crypo-0.0.3.dist-info/RECORD
