Metadata-Version: 2.4
Name: crypo
Version: 0.0.3
Summary: ⚠️ Typo protection: You probably meant 'crypto' or 'pycryptodome'. Defensive registration against typosquatting.
Author: Security Researcher
License-Expression: MIT
Project-URL: Correct Package (pycryptodome), https://pypi.org/project/pycryptodome/
Project-URL: Correct Package (cryptography), https://pypi.org/project/cryptography/
Project-URL: Why This Exists, https://en.wikipedia.org/wiki/Typosquatting
Keywords: typosquatting,security,crypto,typo,protection
Classifier: Development Status :: 1 - Planning
Classifier: Intended Audience :: Developers
Classifier: Programming Language :: Python :: 3
Classifier: Topic :: Security
Requires-Python: >=3.6
Dynamic: requires-python
